jennie/__init__.py
jennie/configration.py
jennie/constants.py
jennie/autobot/__init__.py
jennie/autobot/autobotnlp.py
jennie/autobot/constants.py
jennie/constants/__init__.py
jennie/constants/inputmessage.py
jennie/constants/protocol.py
jennie/constants/responses.py
jennie/constants/urls.py
jennie/events/__init__.py
jennie/events/events.py
jennie/events/rule_engine.py
jennie/events/angular/__init__.py
jennie/events/angular/add_ng_library.py
jennie/events/angular/angular_automations.py
jennie/events/angular/angular_ui_lib.py
jennie/events/angular/copy_angular_component.py
jennie/events/angular/create_angular_component.py
jennie/events/angular/create_angular_module.py
jennie/events/angular/create_angular_module_routing.py
jennie/events/angular/create_angular_services.py
jennie/events/angular/create_multiple_angular_components.py
jennie/events/angular/update_angular_json.py
jennie/events/angular/update_angular_modules.py
jennie/events/angular/update_angular_routes.py
jennie/events/common/__init__.py
jennie/events/common/add_script_to_index.py
jennie/events/common/download_files.py
jennie/events/common/replace_in_file.py
jennie/events/django/__init__.py
jennie/events/django/django_automations.py
jennie/events/django/update_settings_py.py
jennie/events/django/update_urls_py.py
jennie/events/npm/__init__.py
jennie/events/npm/install_npm_libraries.py
jennie/events/py/__init__.py
jennie/events/py/create_python_package.py
jennie/events/py/install_python3_libraries.py
jennie/events/reactjs/__init__.py
jennie/events/reactjs/create_react_js_component.py
jennie/events/reactjs/create_reactjs_component.py
jennie/protocols/__init__.py
jennie/protocols/automationprotocol.py
jennie/protocols/make_files.py
jennie/protocols/angular/__init__.py
jennie/protocols/angular/uilib.py
jennie/protocols/django/__init__.py
jennie/protocols/docker/__init__.py
jennie/protocols/nodejs/__init__.py
jennie/protocols/packer/__init__.py
jennie/protocols/reactjs/__init__.py
ask_jennie-1.0.0.dist-info/METADATA
ask_jennie-1.0.0.dist-info/WHEEL
ask_jennie-1.0.0.dist-info/entry_points.txt
ask_jennie-1.0.0.dist-info/top_level.txt
ask_jennie-1.0.0.dist-info/RECORD
