Metadata-Version: 2.1
Name: ask-jennie
Version: 1.0.0
Summary: The package targets protocol for uploading and reusing task and libraries
Home-page: https://github.com/Ask-Jennie/jennie
Author: ASK Jennie
Author-email: Jennie Automation Protocol <saurabh@ask-jennie.com>
Classifier: License :: OSI Approved :: MIT License
Classifier: Programming Language :: Python :: 3
Classifier: Programming Language :: Python :: 3.7
Requires-Dist: requests
Requires-Dist: bs4
Requires-Dist: xlrd
